MANIFEST.in
README
setup.py
django_multiblogs.egg-info/PKG-INFO
django_multiblogs.egg-info/SOURCES.txt
django_multiblogs.egg-info/dependency_links.txt
django_multiblogs.egg-info/top_level.txt
django_multiblogs.egg-info/zip-safe
multiblogs/__init__.py
multiblogs/admin.py
multiblogs/forms.py
multiblogs/managers.py
multiblogs/models.py
multiblogs/tests.py
multiblogs/urls.py
multiblogs/views.py
multiblogs/templatetags/__init__.py
multiblogs/templatetags/multiblog_tags.py