Metadata-Version: 1.0
Name: django-multiblogs
Version: 0.1.4
Summary: An application for managing multiple blogs, and even *gasp* blog "sets".
Home-page: http://github.com/powellc/django-multiblogs
Author: Colin Powell
Author-email: colin@onecardinal.com
License: BSD
Download-URL: http://github.com/powellc/django-multiblogs/downloads
Platform: UNKNOWN
Classifier: Development Status :: 4 - Beta
Classifier: Environment :: Web Environment
Classifier: Intended Audience :: Developers
Classifier: License :: OSI Approved :: BSD License
Classifier: Operating System :: OS Independent
Classifier: Programming Language :: Python
Classifier: Framework :: Django
